README
setup.py
src/firstdjango/__init__.py
src/firstdjango/models.py
src/firstdjango/tests.py
src/firstdjango/testsettings.py
src/firstdjango.egg-info/PKG-INFO
src/firstdjango.egg-info/SOURCES.txt
src/firstdjango.egg-info/dependency_links.txt
src/firstdjango.egg-info/requires.txt
src/firstdjango.egg-info/top_level.txt