Metadata-Version: 1.1
Name: firstdjango
Version: 1.0
Summary: My first Django app
Home-page: http://akasig.org
Author: Jean Millerat
Author-email: sig@akasig.org
License: AGPL
Platform: UNKNOWN
Classifier: Development Status :: 1 - Planning
Classifier: Framework :: Django
Classifier: Intended Audience :: Developers
Classifier: License :: OSI Approved :: GNU Affero General Public License v3 or later (AGPLv3+)
Classifier: Operating System :: OS Independent
Classifier: Programming Language :: Python
Classifier: Topic :: Internet :: WWW/HTTP
